{
	"info": {
		"_postman_id": "bf860799-8927-4b49-ab00-1dd23ffa829a",
		"name": "desafio_tecnico",
		"schema": "https://schema.getpostman.com/json/collection/v2.1.0/collection.json",
		"_exporter_id": "25030199"
	},
	"item": [
		{
			"name": "Clientes",
			"request": {
				"auth": {
					"type": "noauth"
				},
				"method": "GET",
				"header": [],
				"url": {
					"raw": "http://localhost:3000/clientes?search=ACME&page=1&limit=10",
					"protocol": "http",
					"host": [
						"localhost"
					],
					"port": "3000",
					"path": [
						"clientes"
					],
					"query": [
						{
							"key": "search",
							"value": "ACME"
						},
						{
							"key": "page",
							"value": "1"
						},
						{
							"key": "limit",
							"value": "10"
						}
					]
				}
			},
			"response": []
		},
		{
			"name": "Clientes",
			"request": {
				"auth": {
					"type": "noauth"
				},
				"method": "POST",
				"header": [],
				"body": {
					"mode": "raw",
					"raw": "{\r\n  \"idUsuario\": 1,\r\n  \"Codigo\": \"C001\",\r\n  \"Nome\": \"ACME LTDA\",\r\n  \"CPF_CNPJ\": \"12345678000190\",\r\n  \"CEP\": 13280000,\r\n  \"Logradouro\": \"Rua X\",\r\n  \"Endereco\": \"Rua X, Centro\",\r\n  \"Numero\": \"123\",\r\n  \"Bairro\": \"Centro\",\r\n  \"Cidade\": \"Vinhedo\",\r\n  \"UF\": \"SP\",\r\n  \"Complemento\": \"Sala 2\",\r\n  \"Fone\": \"19999999999\",\r\n  \"LimiteCredito\": 5000,\r\n  \"Validade\": \"2026-12-31\"\r\n}",
					"options": {
						"raw": {
							"language": "json"
						}
					}
				},
				"url": {
					"raw": "http://localhost:3000/clientes",
					"protocol": "http",
					"host": [
						"localhost"
					],
					"port": "3000",
					"path": [
						"clientes"
					]
				}
			},
			"response": []
		},
		{
			"name": "Clientes",
			"request": {
				"auth": {
					"type": "noauth"
				},
				"method": "PUT",
				"header": [],
				"body": {
					"mode": "raw",
					"raw": "{\r\n  \"Nome\": \"ACME LTDA - Matriz\",\r\n  \"LimiteCredito\": 8000,\r\n  \"UF\": \"SP\"\r\n}",
					"options": {
						"raw": {
							"language": "json"
						}
					}
				},
				"url": {
					"raw": "http://localhost:3000/clientes/:id",
					"protocol": "http",
					"host": [
						"localhost"
					],
					"port": "3000",
					"path": [
						"clientes",
						":id"
					],
					"variable": [
						{
							"key": "id",
							"value": "1"
						}
					]
				}
			},
			"response": []
		},
		{
			"name": "Clientes",
			"request": {
				"auth": {
					"type": "noauth"
				},
				"method": "DELETE",
				"header": [],
				"url": {
					"raw": "http://localhost:3000/clientes/:id",
					"protocol": "http",
					"host": [
						"localhost"
					],
					"port": "3000",
					"path": [
						"clientes",
						":id"
					],
					"variable": [
						{
							"key": "id",
							"value": "1"
						}
					]
				}
			},
			"response": []
		}
	],
	"event": [
		{
			"listen": "prerequest",
			"script": {
				"type": "text/javascript",
				"packages": {},
				"exec": [
					""
				]
			}
		},
		{
			"listen": "test",
			"script": {
				"type": "text/javascript",
				"packages": {},
				"exec": [
					""
				]
			}
		}
	],
	"variable": [
		{
			"key": "url\n",
			"value": "http://localhost:3000",
			"type": "string"
		}
	]
}